mortal_parse/__init__.py
mortal_parse/sqlparse_main.cpython-38-x86_64-linux-gnu.so
mortal_parse-4.3.0.dist-info/METADATA
mortal_parse-4.3.0.dist-info/WHEEL
mortal_parse-4.3.0.dist-info/top_level.txt
mortal_parse-4.3.0.dist-info/RECORD
