Metadata-Version: 2.1
Name: mortal_parse
Version: 4.3.0
Summary: mortal工具集::mortal_parse
Home-page: https://www.example.com
Author: Mortal
Author-email: mortal9098@163.com
License: MIT
Classifier: Development Status :: 4 - Beta
Classifier: Programming Language :: Python :: 3
Classifier: Programming Language :: Python :: 3.8
Classifier: Operating System :: POSIX :: Linux
Classifier: Intended Audience :: Developers
Requires-Python: >=3.7
Requires-Dist: ms9
Requires-Dist: mortal-var
Requires-Dist: moz-sql-parser
Requires-Dist: ply
